setup.py
cs/__init__.py
cs.tags.egg-info/PKG-INFO
cs.tags.egg-info/SOURCES.txt
cs.tags.egg-info/dependency_links.txt
cs.tags.egg-info/entry_points.txt
cs.tags.egg-info/namespace_packages.txt
cs.tags.egg-info/not-zip-safe
cs.tags.egg-info/paster_plugins.txt
cs.tags.egg-info/requires.txt
cs.tags.egg-info/top_level.txt
cs/tags/README.txt
cs/tags/__init__.py
cs/tags/clouds.py
cs/tags/configure.zcml
cs/tags/interfaces.py
cs/tags/tags.py
cs/tags/tests.py
cs/tags/browser/__init__.py
cs/tags/browser/tags.py
docs/HISTORY.txt
docs/INSTALL.txt
docs/LICENSE.GPL
docs/LICENSE.txt
