Metadata-Version: 1.0
Name: cs.tags
Version: 0.1
Summary: UNKNOWN
Home-page: http://code.codesyntax.com/public/cs.tags
Author: CodeSyntax
Author-email: fquintana@codesyntax.com
License: GPL
Keywords: tag clouds tagging engine
Platform: UNKNOWN
Classifier: Framework :: Zope3
Classifier: Programming Language :: Python
Classifier: Topic :: Software Development :: Libraries :: Python Modules
